irx/__init__.py
irx/builders/__init__.py
irx/builders/base.py
irx/builders/llvmliteir.py
irx/py.typed
irx/symbol_table.py
irx/system.py
irx/tools/__init__.py
irx/tools/typing.py
pyirx-1.4.0.dist-info/LICENSE
pyirx-1.4.0.dist-info/METADATA
pyirx-1.4.0.dist-info/WHEEL
pyirx-1.4.0.dist-info/RECORD
